md_to_slack_blocks/__init__.py
md_to_slack_blocks/main.py
md_to_slack_blocks-0.1.0.dist-info/METADATA
md_to_slack_blocks-0.1.0.dist-info/WHEEL
md_to_slack_blocks-0.1.0.dist-info/top_level.txt
md_to_slack_blocks-0.1.0.dist-info/RECORD
