Metadata-Version: 2.4
Name: md-to-slack-blocks
Version: 0.1.0
Summary: A simple python library to convert markdown to the Slack blocks
Author-email: Karthikeya Meesala <mkarthikeya41@gmail.com>
License-Expression: MIT
Requires-Python: >=3.8
